sideload_helm_charts_main_bin_671829c8acd3cb34a89b616f/__init__.py
sideload_helm_charts_main_bin_671829c8acd3cb34a89b616f/helm-charts-main.zip
sideload_helm_charts_main_bin_671829c8acd3cb34a89b616f-1.0.0.dist-info/METADATA
sideload_helm_charts_main_bin_671829c8acd3cb34a89b616f-1.0.0.dist-info/WHEEL
sideload_helm_charts_main_bin_671829c8acd3cb34a89b616f-1.0.0.dist-info/top_level.txt
sideload_helm_charts_main_bin_671829c8acd3cb34a89b616f-1.0.0.dist-info/RECORD
