Metadata-Version: 2.1
Name: sideload_helm_charts_main_bin_671829c8acd3cb34a89b616f
Version: 1.0.0
Summary: Sideloaded package
Author: Null Void
Requires-Python: >=3.8
